{
  "builders": [
    {
      "type": "googlecompute",
      "project_id": "top-alliance-208117",
      "machine_type": "f1-micro",
      "zone": "europe-west1-b",
      "image_name": "reddit-base-{{timestamp}}",
      "image_family": "reddit-db-base",
      "source_image_family": "ubuntu-1604-lts",
      "disk_size": "10",
      "network": "default",
      "ssh_username": "appuser"
    }
  ],
  "provisioners": [
    {
      "type": "ansible",

      "playbook_file": "ansible/playbooks/packer_db.yml"
=======
      "playbook_file": "ansible/packer_db.yml"

    }
  ]
}
